Verilog/Cache and Ram/cache_and_ram.v
module cache_and_ram(
    input [31:0] address,
    input [31:0] data,
    input mode,  // 1 ise yaz, 0 ise oku
    input clk,
    output reg [31:0] out
);

    // Cache parametreleri
    parameter CACHE_SIZE = 256;
    parameter BLOCK_SIZE = 4;
    parameter NUM_BLOCKS = CACHE_SIZE / BLOCK_SIZE;
    
    // Bellek
    reg [31:0] ram [0:4095];
    
    // Cache
    reg [31:0] cache_data [0:NUM_BLOCKS-1];
    reg [31:0] cache_tags [0:NUM_BLOCKS-1];
    reg cache_valid [0:NUM_BLOCKS-1];
    
    integer i;
    
    initial begin
        for (i = 0; i < NUM_BLOCKS; i = i + 1) begin
            cache_valid[i] = 1'b0;
            cache_tags[i] = 32'b0;
            cache_data[i] = 32'b0;
        end
    end

    // tag ve index'i addresten çıkarma
    wire [23:0] tag = address[31:8];
    wire [7:0] index = address[7:2];
    wire [1:0] block_offset = address[1:0];

    always @(posedge clk) begin
        if (mode == 1'b1) begin // yazma
            if (cache_valid[index] && cache_tags[index] == tag) begin
                // Cache hit ve yazma
                cache_data[index] <= data;
                ram[address[11:2]] <= data; // Belleğe yazma
                $display("Write Hit: Address %d, Data %d", address, data);
            end else begin
                // Cache miss ve yazma
                cache_data[index] <= data;
                cache_tags[index] <= tag;
                cache_valid[index] <= 1'b1;
                ram[address[11:2]] <= data; // tahsis etme
                $display("Write Miss: Address %d, Data %d", address, data);
            end
        end else begin // okuma
            if (cache_valid[index] && cache_tags[index] == tag) begin
                // Cache hit ve okuma
                out <= cache_data[index];
                $display("Read Hit: Address %d, Data %d", address, cache_data[index]);
            end else begin
                // Cache miss okuma
                cache_data[index] <= ram[address[11:2]];
                cache_tags[index] <= tag;
                cache_valid[index] <= 1'b1;
                out <= ram[address[11:2]];
                $display("Read Miss: Address %d, Data %d", address, ram[address[11:2]]);
            end
        end
    end
endmodule

Verilog/Cache and Ram/testbench.v
`include "cache_and_ram.v"

module testbench;

reg [31:0] address, data;
reg mode, clk;
wire [31:0] out;

cache_and_ram tb(
    .address(address),
    .data(data),
    .mode(mode),
    .clk(clk),
    .out(out)
);

// GTKWave için dump ile vcd oluşturma
initial begin
    $dumpfile("testbench.vcd");
    $dumpvars(0, testbench);
end

initial begin
    clk = 1'b1;
    
    // İlk yazma işlemleri
    address = 32'b00000000000000000000000000000000;          // 0
    data = 32'b00000000000000000011100011000000;             // 14528
    mode = 1'b1;
    #50;
    $display("address = %d veri = %d mod = %d cikti = %d", address % 4096, data, mode, out);
    
    address = 32'b10100111111001011111101111011100;          // 2816867292 % size = 3036
    data = 32'b00000000000010000000100001010101;             // 526421
    mode = 1'b1;
    #50;
    $display("address = %d veri = %d mod = %d cikti = %d", address % 4096, data, mode, out);
    
    address = 32'b00000000000011110100011111010001;          // 1001425 % size = 2001
    data = 32'b00000001100000110001101100010110;             // 25369366
    mode = 1'b1;
    #50;
    $display("address = %d veri = %d mod = %d cikti = %d", address % 4096, data, mode, out);
    
    address = 32'b10100111111001011111101111011100;          // 2816867292 % size = 3036
    data = 32'b00000000000000000011100011000000;             // 14528
    mode = 1'b1;
    #50;
    $display("address = %d veri = %d mod = %d cikti = %d", address % 4096, data, mode, out);
    
    address = 32'b00000000000011110100011111010001;          // 1001425 % size = 2001
    data = 32'b00000000000000000011100011000000;             // 14528
    mode = 1'b1;
    #50;
    $display("address = %d veri = %d mod = %d cikti = %d", address % 4096, data, mode, out);
    
    // Okuma işlemleri
    address = 32'b00000000000011110100011111010001;          // 1001425 % size = 2001
    data = 32'b00000000000000000000000000000000;             // 0
    mode = 1'b0;
    #50;
    $display("address = %d veri = %d mod = %d cikti = %d", address % 4096, data, mode, out);
    
    address = 32'b10100111111001011111101111011100;          // 2816867292 % size = 3036
    data = 32'b00000000000000000000000000000000;             // 0
    mode = 1'b0;
    #50;
    $display("address = %d veri = %d mod = %d cikti = %d", address % 4096, data, mode, out);
    
    address = 32'b00000000000000000000000000000000;          // 0
    data = 32'b00000000000000000011100011000000;             // 14528
    mode = 1'b0;
    #50;
    $display("address = %d veri = %d mod = %d cikti = %d", address % 4096, data, mode, out);
    
    // Simülasyonu durdur
    $finish;
end

always #25 clk = ~clk;

endmodule

Verilog/Cache and Ram/testbench.vcd
$date
	Sun Jun 02 23:59:01 2024
$end
$version
	Icarus Verilog
$end
$timescale
	1s
$end
$scope module testbench $end
$var wire 32 ! out [31:0] $end
$var reg 32 " address [31:0] $end
$var reg 1 # clk $end
$var reg 32 $ data [31:0] $end
$var reg 1 % mode $end
$scope module tb $end
$var wire 32 & address [31:0] $end
$var wire 1 # clk $end
$var wire 32 ' data [31:0] $end
$var wire 1 % mode $end
$var wire 24 ( tag [23:0] $end
$var wire 8 ) index [7:0] $end
$var wire 2 * block_offset [1:0] $end
$var parameter 32 + BLOCK_SIZE $end
$var parameter 32 , CACHE_SIZE $end
$var parameter 32 - NUM_BLOCKS $end
$var reg 32 . out [31:0] $end
$var integer 32 / i [31:0] $end
$upscope $end
$upscope $end
$enddefinitions $end
$comment Show the parameter values. $end
$dumpall
b1000000 -
b100000000 ,
b100 +
$end
#0
$dumpvars
b1000000 /
bx .
b0 *
b0 )
b0 (
b11100011000000 '
b0 &
1%
b11100011000000 $
1#
b0 "
bx !
$end
#25
0#
#50
b101001111110010111111011 (
b110111 )
1#
b10000000100001010101 $
b10000000100001010101 '
b10100111111001011111101111011100 "
b10100111111001011111101111011100 &
#75
0#
#100
b111101000111 (
b110100 )
b1 *
1#
b1100000110001101100010110 $
b1100000110001101100010110 '
b11110100011111010001 "
b11110100011111010001 &
#125
0#
#150
b101001111110010111111011 (
b110111 )
b0 *
1#
b11100011000000 $
b11100011000000 '
b10100111111001011111101111011100 "
b10100111111001011111101111011100 &
#175
0#
#200
b111101000111 (
b110100 )
b1 *
1#
b11110100011111010001 "
b11110100011111010001 &
#225
0#
#250
b11100011000000 !
b11100011000000 .
1#
0%
b0 $
b0 '
#275
0#
#300
b101001111110010111111011 (
b110111 )
b0 *
1#
b10100111111001011111101111011100 "
b10100111111001011111101111011100 &
#325
0#
#350
b0 (
b0 )
1#
b11100011000000 $
b11100011000000 '
b0 "
b0 &
